Workbook

Sheet Levels
A1: Level Name | B1: Creator | C1: Song | D1: ID | E1: Tier | F1: Enjoyment
A2: Clubstep | B2: RobTop | C2: Clubstep | D2: 1 | E2: 2.82 | F2: 6.57 | H2: Esta es la lista de TODOS los niveles, con un total de 8800+ niveles, las hojas de la parte inferior muestran algunas formulas aplicadas y tablas dinamicas
A3: Theory of Everything 2 | B3: RobTop | C3: Theory of Everything 2 | D3: 2 | E3: 3 | F3: 7.18
A4: Deadlocked | B4: RobTop | C4: Deadlocked | D4: 3 | E4: 4.82 | F4: 7.13
A5: demon park | B5: M2coL | C5: Time Machine | D5: 10109 | E5: 2.84 | F5: 5.61
A6: To the Grave | B6: - | C6: Time Machine | D6: 12556 | E6: 3.93 | F6: 5.3
A7: The Nightmare | B7: Jax | C7: Polargeist | D7: 13519 | E7: 1 | F7: 5.81
A8: THE LIGHTNING ROAD | B8: timeless real | C8: Dry Out | D8: 55520 | E8: 1 | F8: 4.9
A9: Extreme Park | B9: Rabbitical | C9: Jumper | D9: 56287 | E9: 6.89 | F9: 6.52
A10: Super Cycles | B10: Jax | C10: Cycles | D10: 57730 | E10: 1.86 | F10: 5.31
A11: yStep | B11: TheRealDarnoc | C11: xStep | D11: 70059 | E11: 1.77 | F11: 5.31
A12: OFFline | B12: Spawn | C12: xStep | D12: 72282 | E12: 1.88 | F12: 5.14
A13: demon world | B13: superhexagon | C13: xStep | D13: 72540 | E13: 8.1 | F13: 4.34
A14: hell and heaven | B14: PIS | C14: Dry Out | D14: 74449 | E14: 4.63 | F14: 6.02
... A860: StandOff | B860: XTHANEX | C860: KzX - Stalemate | D860: 9947368 | E860: 15.4 | F860: 4.33
A861: 10 | B861: T3mpl4te | C861: Uninstall | D861: 9962546 | E861: 14.61 | F861: 6.18
A862: DiamonD | B862: Jerry4 | C862: TheFatRat - Windfall | D862: 9965435 | E862: 15.81 | F862: 5.52
A863: Sound of Infinity | B863: RealSoulDash | C863: Sound of Infinity - F-777 | D863: 9992497 | E863: 10.2 | F863: 7.5
A864: Insomnia | B864: MattMrn | C864: Fijiwiji- Insomnia (F-777 RMX) | D864: 10026842 | E864: 12.67 | F864: 4.33
A865: screamroom | B865: GMD Condor | C865: Xtrullor - Screamroom | D865: 10045444 | E865: 13.73 | F865: 6.85
A866: Hallucinations | B866: Ludicrous | C866: The Hallucination | D866: 10047384 | E866: 15.94 | F866: 5.22
A867: The end of the world | B867: Draykonic | C867: {dj-N} Alls Lost [Full Ver.] | D867: 10065112 | E867: 3.95 | F867: 5.89
A868: Tempest | B868: Triadic | C868: {dj-N} Rain Full | D868: 10092715 | E868: 11.84 | F868: 6.88
A869: SkyLand | B869: softable | C869: =-Orr- Soaring in The Stars -> #NAME? | D869: 10127117 | E869: 3.75 | F869: 6.05
A870: Forsaken Crypts | B870: Green Dragon | C870: Starship Showdown | D870: 10130051 | E870: 11 | F870: 7
A871: Light Years | B871: xSmokes | C871: -Lightspeed- | D871: 10137630 | E871: 18.35 | F871: 5.9
A872: electric offline | B872: Rabb2t | C872: -Lightspeed- | D872: 10150016 | E872: 4.3 | F872: 7.04
A873: Deathrun Rebirth | B873: carapa22 | C873: Fijiwiji- Insomnia (F-777 RMX) | D873: 10162215 | E873: 11.99 | F873: 7
A874: Tricksters Funhouse | B874: LmAnubis | C874: -Clownparty remix- | D874: 10177712 | E874: 10.63 | F874: 6.93
A875: Malfunction | B875: Haru | C875: Redux | D875: 10196027 | E875: 7.22 | F875: 6.5
A876: Paracosm Circles | B876: N1XO | C876: Paracosm | D876: 10197026 | E876: 5.94 | F876: 5.57
A877: Escape Area 51 | B877: s1naptico | C877: Sinusoidal Depleneration | D877: 10198717 | E877: 4.12 | F877: 5.39
A878: Eighto | B878: eskim0 | C878: Jomekka - Eighto | D878: 10213857 | E878: 6.07 | F878: 6.05
A879: Ultimate Demon Mix | B879: Zobros | C879: [TMM43] Ultimate Destruction | D879: 10229235 | E879: 15.69 | F879: 4.94
A880: Sonic Chamber | B880: GMDElite | C880: F-777 - Sonic Blaster | D880: 10235582 | E880: 14.93 | F880: 4.95
A881: Glow Storm | B881: Rob Buck | C881: ParagonX9 - Chaoz Fantasy | D881: 10261137 | E881: 8.85 | F881: 5.22
... A1057: AfterShock | B1057: GuraNuS | C1057: Xtrullor - Earthsplitter | D1057: 13141872 | E1057: 3 | F1057: 5.43
A1058: Eradicator | B1058: Deevoo | C1058: 1077 | D1058: 13155403 | E1058: 7.69 | F1058: 6.64
A1059: Stalker | B1059: oraviram | C1059: -Stalker- | D1059: 13162034 | E1059: 16.91 | F1059: 6.55
A1060: Okibae Breakdown | B1060: Oskux | C1060: Bossfight - Okiba Crackdown | D1060: 13169075 | E1060: 6.86 | F1060: 6.8
A1061: Water Kingdom | B1061: Elzeko | C1061: -Haunted woods- | D1061: 13178781 | E1061: 13.14 | F1061: 4.6
A1062: Disco Caverns | B1062: CairoX | C1062: ~BH~ Hells Maw | D1062: 13183849 | E1062: 11 | F1062: 5.63
A1063: Elemental Melons | B1063: 123Ev4n | C1063: Elemelons | D1063: 13197083 | E1063: 15.02 | F1063: 7.45
A1064: Elemelons 2 | B1064: TheRealSalad | C1064: Elemelons | D1064: 13199224 | E1064: 9.87 | F1064: 6.53
A1065: Neon Cluster | B1065: LmAnubis | C1065: ParagonX9 - Defection | D1065: 13211586 | E1065: 12.33 | F1065: 5.2
A1066: Ichor | B1066: newayz | C1066: Xtrullor - Ichor | D1066: 13216306 | E1066: 8.27 | F1066: 4
A1067: Bassroom | B1067: HoriZon Lights | C1067: Xtrullor - Screamroom | D1067: 13219953 | E1067: 6.7 | F1067: 4.71
A1068: Anima Vendit | B1068: Hdow | C1068: Xtrullor - Screamroom | D1068: 13220947 | E1068: 12.92 | F1068: 7
A1069: Demigod | B1069: Rob Buck | C1069: Xtrullor - Ichor | D1069: 13230816 | E1069: 7 | F1069: 4.33
A1070: Split the System | B1070: EthanLX | C1070: System Split - F-777 | D1070: 13239769 | E1070: 11.04 | F1070: 6
... A1163: The Legend | B1163: ISariaI | C1163: Legend of heroes | D1163: 14193650 | E1163: 11.88 | F1163: 7.5
A1164: Lost Legends | B1164: TDChris02 | C1164: 1077 | D1164: 14274060 | E1164: 9.17 | F1164: 5.9
A1165: Metal Shock III | B1165: SMBlacktime | C1165: Genesis | D1165: 14299100 | E1165: 13.04 | F1165: 6.27
A1166: Supernova | B1166: Zanek184 | C1166: Xtrullor - Supernova | D1166: 14302394 | E1166: 12.98 | F1166: 5.57
A1167: AnotherCircles | B1167: Zyzyx | C1167: NK - Nine Circles (Xtrullor Remix) | D1167: 14309230 | E1167: 6.94 | F1167: 5.53
A1168: Quasar | B1168: Allan | C1168: Genesis | D1168: 14321727 | E1168: 11.91 | F1168: 7.08
A1169: Warhead | B1169: TrueChaos | C1169: NK - Jawbreaker | D1169: 14329459 | E1169: 7.11 | F1169: 6.53
A1170: Spilled Milk | B1170: ErisethSP | C1170: Milky Ways Redux | D1170: 14334093 | E1170: 13 | F1170: 7.13
A1171: Hydragon | B1171: MalZir | C1171: Redemption | D1171: 14342746 | E1171: 11.29 | F1171: 7.33
A1172: Hellish Melody | B1172: RoWey | C1172: Squid Melody [Red Version] | D1172: 14348789 | E1172: 14.36 | F1172: 6.54
A1173: Line Apocalypse | B1173: HDJump | C1173: ParagonX9 - HyperioxX | D1173: 14360708 | E1173: 13.47 | F1173: 5.8
A1174: Ego Death | B1174: Wulzy | C1174: Ego Death | D1174: 14361377 | E1174: 3.41 | F1174: 5.07
A1175: silhouette | B1175: Wolfkami | C1175: Detious & Lockyn - Allure | D1175: 14361565 | E1175: 11.4 | F1175: 4.2
A1176: Deadlocked V2 | B1176: Nik Gambardella | C1176: Deadlocked | D1176: 14365491 | E1176: 9.55 | F1176: 5.3
... A1299: RIP IT | B1299: Galzo | C1299: Rip it | D1299: 16295215 | E1299: 10.02 | F1299: 4.38
A1300: 666 | B1300: dongchi | C1300: [TMM43] Ultimate Destruction | D1300: 16321390 | E1300: 3.18 | F1300: 7.08
A1301: Rebirth | B1301: Iid4sh3riI | C1301: Genesis | D1301: 16327565 | E1301: 7.92 | F1301: 6.38
A1302: Bass Lab | B1302: bloodshot | C1302: ~NK~ DEV-BassDownLow Remix | D1302: 16330911 | E1302: 12.98 | F1302: 6.6
A1303: furyhell | B1303: TheTrueSanji | C1303: Dr. Phonics - Firepower | D1303: 16366743 | E1303: 15.51 | F1303: 5.86
A1304: Pneumatic Tokyo | B1304: Sechsan | C1304: EnV - Pneumatic Tokyo | D1304: 16369578 | E1304: 10.99 | F1304: 6.71
A1305: ChipWorld | B1305: Andromeda GMD | C1305: Untitled chipsounds | D1305: 16408420 | E1305: 9.88 | F1305: 5.36
A1306: Abandoned Machine | B1306: Jeyzor | C1306: Lets Bounce | D1306: 16412338 | E1306: 16.23 | F1306: 6.96
A1307: Pursuit | B1307: Shocksidian | C1307: Pursuit | D1307: 16441569 | E1307: 18.35 | F1307: 4.55
A1308: Excursion | B1308: KingmanTV | C1308: EnV - RPM | D1308: 16444956 | E1308: 11.25 | F1308: 7.25
A1309: Chaos Reactor | B1309: KarelTheGreat | C1309: Xtrullor - Supernova | D1309: 16456999 | E1309: 9.4 | F1309: 7
A1310: Dangerous | B1310: SilverSoul | C1310: Hidden Dangers [DUBSTEP] | D1310: 16469381 | E1310: 7.86 | F1310: 5.33
A1311: Nemesis | B1311: Florent | C1311: Shots Fired (Mafia Pineapple Remix) | D1311: 16500835 | E1311: 4.6 | F1311: 5.61
A1312: Arachnid Temple | B1312: ViPriN | C1312: Lord of the Koopas | D1312: 16557570 | E1312: 14.15 | F1312: 4.92
... A1416: Techno Blast | B1416: Gryllex | C1416: xStep | D1416: 18388332 | E1416: 14.22 | F1416: 5.67
A1417: Z | B1417: Zyzyx | C1417: 1077 | D1417: 18397804 | E1417: 6.22 | F1417: 6.43
A1418: Hell Above | B1418: Maboflo | C1418: Domyeah - Escape from Hell | D1418: 18406722 | E1418: 5.8 | F1418: 4.2
A1419: Dem Travel | B1419: Serponge | C1419: Skybound | D1419: 18421584 | E1419: 8.1 | F1419: 6.11
A1420: love baba | B1420: Zobros | C1420: The Empire Of Toads | D1420: 18478071 | E1420: 17.66 | F1420: 2.94
A1421: Crimson Comodo | B1421: Nwolc | C1421: Comodo | D1421: 18481930 | E1421: 10.4 | F1421: 6.8
A1422: Dismal | B1422: Megaman9 | C1422: Xtrullor Panda Party - Sheol | D1422: 18483771 | E1422: 8.25 | F1422: 4.5
A1423: Beyond The Nature | B1423: JonathanGD | C1423: Jumper - Beyond The Walls | D1423: 18515822 | E1423: 16.75 | F1423: 5.78
A1424: Endorphin Rush | B1424: TamaN | C1424: DuoCore - Endorphins | D1424: 18598146 | E1424: 2.89 | F1424: 7.91
A1425: Divigate | B1425: willy5000 | C1425: Impact Of Emotions | D1425: 18653569 | E1425: 15.35 | F1425: 7.2
A1426: Cyber Chaos | B1426: Hinds | C1426: F-777 - Viper (Full) | D1426: 18674844 | E1426: 18.94 | F1426: 6.64
A1427: Retention | B1427: WOOGI1411 | C1427: Multex - Gravity | D1427: 18697406 | E1427: 21.72 | F1427: 7.97
A1428: Soulless | B1428: EternaswipVMAX | C1428: Your best nightmare (Rmx) Loop | D1428: 18716963 | E1428: 16.04 | F1428: 5.47
A1429: Dear Nostalgists | B1429: TriAxis | C1429: Bossfight - Okiba Crackdown | D1429: 18735780 | E1429: 3.23 | F1429: 6.6
... A1438: Acidulus 8 | B1438: 14Circles | C1438: Acidulus 8 | D1438: 18926501 | E1438: 14.57 | F1438: 7.86
A1439: 48155 | B1439: ViPriN | C1439: Abyss 2 - F-777 | D1439: 18994125 | E1439: 8.7 | F1439: 5.29
A1440: Insomnia II | B1440: Glittershroom | C1440: Fijiwiji- Insomnia (F-777 RMX) | D1440: 19030693 | E1440: 8.06 | F1440: 5
A1441: Visatura | B1441: iI Flow Ii | C1441: Instant Reaction | D1441: 19101053 | E1441: 10.43 | F1441: 6.57
A1442: Mechanical Torment | B1442: Aquatias | C1442: {dj-N} Robotic Nightmares | D1442: 19134395 | E1442: 14.5 | F1442: 5.83
A1443: JeyBreak | B1443: Axthicy | C1443: EnV - Ginseng | D1443: 19183040 | E1443: 8.4 | F1443: 7.78
A1444: Fallen | B1444: jellorain | C1444: Falldown | D1444: 19228405 | E1444: 7 | F1444: 4.5
A1445: Milk Party Redux | B1445: nasgubb | C1445: Milky Ways Redux | D1445: 19270970 | E1445: 12.4 | F1445: 7.8
...

Sheet Creators
A1: Creator | B1: Levels Created | C1: Avg Tier | D1: Avg enjoyment | E1: Hardest Level | F1: Most fun level rate
A2: RobTop | B2: =COUNTIF(Levels!B:B,A2) -> 3 | C2: =IFERROR(AVERAGEIF(Levels!B:B,A2,Levels!E:E),0) -> 3.5466667 | D2: =IFERROR(AVERAGEIF(Levels!B:B,A2,Levels!F:F),0) -> 6.96 | E2: =_xlfn.MAXIFS(Levels!E:E,Levels!B:B,A2) -> 4.82 | F2: =_xlfn.MAXIFS(Levels!F:F,Levels!B:B,A2) -> 7.18
A3: M2coL | B3: =COUNTIF(Levels!B:B,A3) -> 2 | C3: =IFERROR(AVERAGEIF(Levels!B:B,A3,Levels!E:E),0) -> 2.96 | D3: =IFERROR(AVERAGEIF(Levels!B:B,A3,Levels!F:F),0) -> 5.5 | E3: =_xlfn.MAXIFS(Levels!E:E,Levels!B:B,A3) -> 3.08 | F3: =_xlfn.MAXIFS(Levels!F:F,Levels!B:B,A3) -> 5.61
A4: - | B4: =COUNTIF(Levels!B:B,A4) -> 100 | C4: =IFERROR(AVERAGEIF(Levels!B:B,A4,Levels!E:E),0) -> 5.197 | D4: =IFERROR(AVERAGEIF(Levels!B:B,A4,Levels!F:F),0) -> 5.1414 | E4: =_xlfn.MAXIFS(Levels!E:E,Levels!B:B,A4) -> 19.79 | F4: =_xlfn.MAXIFS(Levels!F:F,Levels!B:B,A4) -> 7.4
A5: Jax | B5: =COUNTIF(Levels!B:B,A5) -> 4 | C5: =IFERROR(AVERAGEIF(Levels!B:B,A5,Levels!E:E),0) -> 2.2425 | D5: =IFERROR(AVERAGEIF(Levels!B:B,A5,Levels!F:F),0) -> 5.93 | E5: =_xlfn.MAXIFS(Levels!E:E,Levels!B:B,A5) -> 4.25 | F5: =_xlfn.MAXIFS(Levels!F:F,Levels!B:B,A5) -> 6.56
A6: timeless real | B6: =COUNTIF(Levels!B:B,A6) -> 1 | C6: =IFERROR(AVERAGEIF(Levels!B:B,A6,Levels!E:E),0) -> 1 | D6: =IFERROR(AVERAGEIF(Levels!B:B,A6,Levels!F:F),0) -> 4.9 | E6: =_xlfn.MAXIFS(Levels!E:E,Levels!B:B,A6) -> 1 | F6: =_xlfn.MAXIFS(Levels!F:F,Levels!B:B,A6) -> 4.9
A7: Rabbitical | B7: =COUNTIF(Levels!B:B,A7) -> 13 | C7: =IFERROR(AVERAGEIF(Levels!B:B,A7,Levels!E:E),0) -> 7.7761538 | D7: =IFERROR(AVERAGEIF(Levels!B:B,A7,Levels!F:F),0) -> 6.1684615 | E7: =_xlfn.MAXIFS(Levels!E:E,Levels!B:B,A7) -> 15.82 | F7: =_xlfn.MAXIFS(Levels!F:F,Levels!B:B,A7) -> 8.09
A8: TheRealDarnoc | B8: =COUNTIF(Levels!B:B,A8) -> 11 | C8: =IFERROR(AVERAGEIF(Levels!B:B,A8,Levels!E:E),0) -> 3.0254545 | D8: =IFERROR(AVERAGEIF(Levels!B:B,A8,Levels!F:F),0) -> 5.8645455 | E8: =_xlfn.MAXIFS(Levels!E:E,Levels!B:B,A8) -> 6.07 | F8: =_xlfn.MAXIFS(Levels!F:F,Levels!B:B,A8) -> 6.33
A9: Spawn | B9: =COUNTIF(Levels!B:B,A9) -> 1 | C9: =IFERROR(AVERAGEIF(Levels!B:B,A9,Levels!E:E),0) -> 1.88 | D9: =IFERROR(AVERAGEIF(Levels!B:B,A9,Levels!F:F),0) -> 5.14 | E9: =_xlfn.MAXIFS(Levels!E:E,Levels!B:B,A9) -> 1.88 | F9: =_xlfn.MAXIFS(Levels!F:F,Levels!B:B,A9) -> 5.14
A10: superhexagon | B10: =COUNTIF(Levels!B:B,A10) -> 1 | C10: =IFERROR(AVERAGEIF(Levels!B:B,A10,Levels!E:E),0) -> 8.1 | D10: =IFERROR(AVERAGEIF(Levels!B:B,A10,Levels!F:F),0) -> 4.34 | E10: =_xlfn.MAXIFS(Levels!E:E,Levels!B:B,A10) -> 8.1 | F10: =_xlfn.MAXIFS(Levels!F:F,Levels!B:B,A10) -> 4.34
A11: PIS | B11: =COUNTIF(Levels!B:B,A11) -> 5 | C11: =IFERROR(AVERAGEIF(Levels!B:B,A11,Levels!E:E),0) -> 5.37 | D11: =IFERROR(AVERAGEIF(Levels!B:B,A11,Levels!F:F),0) -> 5.872 | E11: =_xlfn.MAXIFS(Levels!E:E,Levels!B:B,A11) -> 7.17 | F11: =_xlfn.MAXIFS(Levels!F:F,Levels!B:B,A11) -> 6.23
A12: mrlee | B12: =COUNTIF(Levels!B:B,A12) -> 1 | C12: =IFERROR(AVERAGEIF(Levels!B:B,A12,Levels!E:E),0) -> 5.03 | D12: =IFERROR(AVERAGEIF(Levels!B:B,A12,Levels!F:F),0) -> 4.77 | E12: =_xlfn.MAXIFS(Levels!E:E,Levels!B:B,A12) -> 5.03 | F12: =_xlfn.MAXIFS(Levels!F:F,Levels!B:B,A12) -> 4.77 | H12: Z
A13: MaJackO | B13: =COUNTIF(Levels!B:B,A13) -> 17 | C13: =IFERROR(AVERAGEIF(Levels!B:B,A13,Levels!E:E),0) -> 8.2094118 | D13: =IFERROR(AVERAGEIF(Levels!B:B,A13,Levels!F:F),0) -> 5.1652941 | E13: =_xlfn.MAXIFS(Levels!E:E,Levels!B:B,A13) -> 16.88 | F13: =_xlfn.MAXIFS(Levels!F:F,Levels!B:B,A13) -> 6.88
A14: Vlacc | B14: =COUNTIF(Levels!B:B,A14) -> 13 | C14: =IFERROR(AVERAGEIF(Levels!B:B,A14,Levels!E:E),0) -> 15.998462 | D14: =IFERROR(AVERAGEIF(Levels!B:B,A14,Levels!F:F),0) -> 7.54 | E14: =_xlfn.MAXIFS(Levels!E:E,Levels!B:B,A14) -> 31 | F14: =_xlfn.MAXIFS(Levels!F:F,Levels!B:B,A14) -> 8.95
A15: Coke | B15: =COUNTIF(Levels!B:B,A15) -> 1 | C15: =IFERROR(AVERAGEIF(Levels!B:B,A15,Levels!E:E),0) -> 1.01 | D15: =IFERROR(AVERAGEIF(Levels!B:B,A15,Levels!F:F),0) -> 5.7 | E15: =_xlfn.MAXIFS(Levels!E:E,Levels!B:B,A15) -> 1.01 | F15: =_xlfn.MAXIFS(Levels!F:F,Levels!B:B,A15) -> 5.7
A16: Tagging | B16: =COUNTIF(Levels!B:B,A16) -> 2 | C16: =IFERROR(AVERAGEIF(Levels!B:B,A16,Levels!E:E),0) -> 5.92 | D16: =IFERROR(AVERAGEIF(Levels!B:B,A16,Levels!F:F),0) -> 5.785 | E16: =_xlfn.MAXIFS(Levels!E:E,Levels!B:B,A16) -> 6.11 | F16: =_xlfn.MAXIFS(Levels!F:F,Levels!B:B,A16) -> 5.97
A17: DemonBestGG | B17: =COUNTIF(Levels!B:B,A17) -> 4 | C17: =IFERROR(AVERAGEIF(Levels!B:B,A17,Levels!E:E),0) -> 4.1875 | D17: =IFERROR(AVERAGEIF(Levels!B:B,A17,Levels!F:F),0) -> 5.43 | E17: =_xlfn.MAXIFS(Levels!E:E,Levels!B:B,A17) -> 6 | F17: =_xlfn.MAXIFS(Levels!F:F,Levels!B:B,A17) -> 5.89
A18: Partition | B18: =COUNTIF(Levels!B:B,A18) -> 2 | C18: =IFERROR(AVERAGEIF(Levels!B:B,A18,Levels!E:E),0) -> 3.41 | D18: =IFERROR(AVERAGEIF(Levels!B:B,A18,Levels!F:F),0) -> 6.09 | E18: =_xlfn.MAXIFS(Levels!E:E,Levels!B:B,A18) -> 4.81 | F18: =_xlfn.MAXIFS(Levels!F:F,Levels!B:B,A18) -> 6.47
A19: Back | B19: =COUNTIF(Levels!B:B,A19) -> 1 | C19: =IFERROR(AVERAGEIF(Levels!B:B,A19,Levels!E:E),0) -> 8.23 | D19: =IFERROR(AVERAGEIF(Levels!B:B,A19,Levels!F:F),0) -> 6.31 | E19: =_xlfn.MAXIFS(Levels!E:E,Levels!B:B,A19) -> 8.23 | F19: =_xlfn.MAXIFS(Levels!F:F,Levels!B:B,A19) -> 6.31
A20: tunar98 | B20: =COUNTIF(Levels!B:B,A20) -> 5 | C20: =IFERROR(AVERAGEIF(Levels!B:B,A20,Levels!E:E),0) -> 4.726 | D20: =IFERROR(AVERAGEIF(Levels!B:B,A20,Levels!F:F),0) -> 5.876 | E20: =_xlfn.MAXIFS(Levels!E:E,Levels!B:B,A20) -> 7.62 | F20: =_xlfn.MAXIFS(Levels!F:F,Levels!B:B,A20) -> 7.13
A21: Hiroquet | B21: =COUNTIF(Levels!B:B,A21) -> 3 | C21: =IFERROR(AVERAGEIF(Levels!B:B,A21,Levels!E:E),0) -> 6.6 | D21: =IFERROR(AVERAGEIF(Levels!B:B,A21,Levels!F:F),0) -> 6.1766667 | E21: =_xlfn.MAXIFS(Levels!E:E,Levels!B:B,A21) -> 9.43 | F21: =_xlfn.MAXIFS(Levels!F:F,Levels!B:B,A21) -> 6.65
A22: The Carrot | B22: =COUNTIF(Levels!B:B,A22) -> 2 | C22: =IFERROR(AVERAGEIF(Levels!B:B,A22,Levels!E:E),0) -> 6.58 | D22: =IFERROR(AVERAGEIF(Levels!B:B,A22,Levels!F:F),0) -> 4.895 | E22: =_xlfn.MAXIFS(Levels!E:E,Levels!B:B,A22) -> 6.96 | F22: =_xlfn.MAXIFS(Levels!F:F,Levels!B:B,A22) -> 5.1
A23: TheRealZust | B23: =COUNTIF(Levels!B:B,A23) -> 1 | C23: =IFERROR(AVERAGEIF(Levels!B:B,A23,Levels!E:E),0) -> 17.74 | D23: =IFERROR(AVERAGEIF(Levels!B:B,A23,Levels!F:F),0) -> 3.35 | E23: =_xlfn.MAXIFS(Levels!E:E,Levels!B:B,A23) -> 17.74 | F23: =_xlfn.MAXIFS(Levels!F:F,Levels!B:B,A23) -> 3.35
A24: LunarSimg | B24: =COUNTIF(Levels!B:B,A24) -> 11 | C24: =IFERROR(AVERAGEIF(Levels!B:B,A24,Levels!E:E),0) -> 10.885455 | D24: =IFERROR(AVERAGEIF(Levels!B:B,A24,Levels!F:F),0) -> 6.2745455 | E24: =_xlfn.MAXIFS(Levels!E:E,Levels!B:B,A24) -> 15.9 | F24: =_xlfn.MAXIFS(Levels!F:F,Levels!B:B,A24) -> 8.2
... A961: zinkzeta | B961: =COUNTIF(Levels!B:B,A961) -> 1 | C961: =IFERROR(AVERAGEIF(Levels!B:B,A961,Levels!E:E),0) -> 17 | D961: =IFERROR(AVERAGEIF(Levels!B:B,A961,Levels!F:F),0) -> 6 | E961: =_xlfn.MAXIFS(Levels!E:E,Levels!B:B,A961) -> 17 | F961: =_xlfn.MAXIFS(Levels!F:F,Levels!B:B,A961) -> 6
A962: 1374 | B962: =COUNTIF(Levels!B:B,A962) -> 2 | C962: =IFERROR(AVERAGEIF(Levels!B:B,A962,Levels!E:E),0) -> 4.54 | D962: =IFERROR(AVERAGEIF(Levels!B:B,A962,Levels!F:F),0) -> 7.41 | E962: =_xlfn.MAXIFS(Levels!E:E,Levels!B:B,A962) -> 6.92 | F962: =_xlfn.MAXIFS(Levels!F:F,Levels!B:B,A962) -> 8.23
A963: Sakana | B963: =COUNTIF(Levels!B:B,A963) -> 1 | C963: =IFERROR(AVERAGEIF(Levels!B:B,A963,Levels!E:E),0) -> 12 | D963: =IFERROR(AVERAGEIF(Levels!B:B,A963,Levels!F:F),0) -> 6 | E963: =_xlfn.MAXIFS(Levels!E:E,Levels!B:B,A963) -> 12 | F963: =_xlfn.MAXIFS(Levels!F:F,Levels!B:B,A963) -> 6
A964: Kohtpojiep | B964: =COUNTIF(Levels!B:B,A964) -> 1 | C964: =IFERROR(AVERAGEIF(Levels!B:B,A964,Levels!E:E),0) -> 20.6 | D964: =IFERROR(AVERAGEIF(Levels!B:B,A964,Levels!F:F),0) -> 2.9 | E964: =_xlfn.MAXIFS(Levels!E:E,Levels!B:B,A964) -> 20.6 | F964: =_xlfn.MAXIFS(Levels!F:F,Levels!B:B,A964) -> 2.9
A965: Glaid | B965: =COUNTIF(Levels!B:B,A965) -> 2 | C965: =IFERROR(AVERAGEIF(Levels!B:B,A965,Levels!E:E),0) -> 9.75 | D965: =IFERROR(AVERAGEIF(Levels!B:B,A965,Levels!F:F),0) -> 6.265 | E965: =_xlfn.MAXIFS(Levels!E:E,Levels!B:B,A965) -> 13.1 | F965: =_xlfn.MAXIFS(Levels!F:F,Levels!B:B,A965) -> 6.33
A966: Chom | B966: =COUNTIF(Levels!B:B,A966) -> 1 | C966: =IFERROR(AVERAGEIF(Levels!B:B,A966,Levels!E:E),0) -> 23 | D966: =IFERROR(AVERAGEIF(Levels!B:B,A966,Levels!F:F),0) -> 6 | E966: =_xlfn.MAXIFS(Levels!E:E,Levels!B:B,A966) -> 23 | F966: =_xlfn.MAXIFS(Levels!F:F,Levels!B:B,A966) -> 6
A967: WSKKung | B967: =COUNTIF(Levels!B:B,A967) -> 1 | C967: =IFERROR(AVERAGEIF(Levels!B:B,A967,Levels!E:E),0) -> 5.35 | D967: =IFERROR(AVERAGEIF(Levels!B:B,A967,Levels!F:F),0) -> 7.08 | E967: =_xlfn.MAXIFS(Levels!E:E,Levels!B:B,A967) -> 5.35 | F967: =_xlfn.MAXIFS(Levels!F:F,Levels!B:B,A967) -> 7.08
A968: Alex112300 | B968: =COUNTIF(Levels!B:B,A968) -> 12 | C968: =IFERROR(AVERAGEIF(Levels!B:B,A968,Levels!E:E),0) -> 6.4981818 | D968: =IFERROR(AVERAGEIF(Levels!B:B,A968,Levels!F:F),0) -> 6.4216667 | E968: =_xlfn.MAXIFS(Levels!E:E,Levels!B:B,A968) -> 19.75 | F968: =_xlfn.MAXIFS(Levels!F:F,Levels!B:B,A968) -> 7.5
A969: GirlyAle02 | B969: =COUNTIF(Levels!B:B,A969) -> 4 | C969: =IFERROR(AVERAGEIF(Levels!B:B,A969,Levels!E:E),0) -> 1.8675 | D969: =IFERROR(AVERAGEIF(Levels!B:B,A969,Levels!F:F),0) -> 6.9575 | E969: =_xlfn.MAXIFS(Levels!E:E,Levels!B:B,A969) -> 2.84 | F969: =_xlfn.MAXIFS(Levels!F:F,Levels!B:B,A969) -> 7.61
A970: Stevstyles | B970: =COUNTIF(Levels!B:B,A970) -> 1 | C970: =IFERROR(AVERAGEIF(Levels!B:B,A970,Levels!E:E),0) -> 3.64 | D970: =IFERROR(AVERAGEIF(Levels!B:B,A970,Levels!F:F),0) -> 5.6 | E970: =_xlfn.MAXIFS(Levels!E:E,Levels!B:B,A970) -> 3.64 | F970: =_xlfn.MAXIFS(Levels!F:F,Levels!B:B,A970) -> 5.6
A971: teamodyssey | B971: =COUNTIF(Levels!B:B,A971) -> 2 | C971: =IFERROR(AVERAGEIF(Levels!B:B,A971,Levels!E:E),0) -> 17.25 | D971: =IFERROR(AVERAGEIF(Levels!B:B,A971,Levels!F:F),0) -> 5.75 | E971: =_xlfn.MAXIFS(Levels!E:E,Levels!B:B,A971) -> 18 | F971: =_xlfn.MAXIFS(Levels!F:F,Levels!B:B,A971) -> 7
A972: Djdvd17 | B972: =COUNTIF(Levels!B:B,A972) -> 1 | C972: =IFERROR(AVERAGEIF(Levels!B:B,A972,Levels!E:E),0) -> 9.86 | D972: =IFERROR(AVERAGEIF(Levels!B:B,A972,Levels!F:F),0) -> 5.75 | E972: =_xlfn.MAXIFS(Levels!E:E,Levels!B:B,A972) -> 9.86 | F972: =_xlfn.MAXIFS(Levels!F:F,Levels!B:B,A972) -> 5.75
A973: CreatorDiana | B973: =COUNTIF(Levels!B:B,A973) -> 1 | C973: =IFERROR(AVERAGEIF(Levels!B:B,A973,Levels!E:E),0) -> 2.66 | D973: =IFERROR(AVERAGEIF(Levels!B:B,A973,Levels!F:F),0) -> 5.67 | E973: =_xlfn.MAXIFS(Levels!E:E,Levels!B:B,A973) -> 2.66 | F973: =_xlfn.MAXIFS(Levels!F:F,Levels!B:B,A973) -> 5.67
A974: Cloud72 | B974: =COUNTIF(Levels!B:B,A974) -> 1 | C974: =IFERROR(AVERAGEIF(Levels!B:B,A974,Levels!E:E),0) -> 13.78 | D974: =IFERROR(AVERAGEIF(Levels!B:B,A974,Levels!F:F),0) -> 6.4 | E974: =_xlfn.MAXIFS(Levels!E:E,Levels!B:B,A974) -> 13.78 | F974: =_xlfn.MAXIFS(Levels!F:F,Levels!B:B,A974) -> 6.4
... A1398: Americat5 | B1398: =COUNTIF(Levels!B:B,A1398) -> 1 | C1398: =IFERROR(AVERAGEIF(Levels!B:B,A1398,Levels!E:E),0) -> 3.14 | D1398: =IFERROR(AVERAGEIF(Levels!B:B,A1398,Levels!F:F),0) -> 7.93 | E1398: =_xlfn.MAXIFS(Levels!E:E,Levels!B:B,A1398) -> 3.14 | F1398: =_xlfn.MAXIFS(Levels!F:F,Levels!B:B,A1398) -> 7.93
A1399: 45744574 | B1399: =COUNTIF(Levels!B:B,A1399) -> 2 | C1399: =IFERROR(AVERAGEIF(Levels!B:B,A1399,Levels!E:E),0) -> 6.655 | D1399: =IFERROR(AVERAGEIF(Levels!B:B,A1399,Levels!F:F),0) -> 6.82 | E1399: =_xlfn.MAXIFS(Levels!E:E,Levels!B:B,A1399) -> 7.67 | F1399: =_xlfn.MAXIFS(Levels!F:F,Levels!B:B,A1399) -> 7.64
A1400: Diabeticus | B1400: =COUNTIF(Levels!B:B,A1400) -> 1 | C1400: =IFERROR(AVERAGEIF(Levels!B:B,A1400,Levels!E:E),0) -> 11 | D1400: =IFERROR(AVERAGEIF(Levels!B:B,A1400,Levels!F:F),0) -> 6.67 | E1400: =_xlfn.MAXIFS(Levels!E:E,Levels!B:B,A1400) -> 11 | F1400: =_xlfn.MAXIFS(Levels!F:F,Levels!B:B,A1400) -> 6.67
A1401: JHYMHMHY | B1401: =COUNTIF(Levels!B:B,A1401) -> 3 | C1401: =IFERROR(AVERAGEIF(Levels!B:B,A1401,Levels!E:E),0) -> 4.2033333 | D1401: =IFERROR(AVERAGEIF(Levels!B:B,A1401,Levels!F:F),0) -> 6.5 | E1401: =_xlfn.MAXIFS(Levels!E:E,Levels!B:B,A1401) -> 6.25 | F1401: =_xlfn.MAXIFS(Levels!F:F,Levels!B:B,A1401) -> 7.1
A1402: HugoLA | B1402: =COUNTIF(Levels!B:B,A1402) -> 2 | C1402: =IFERROR(AVERAGEIF(Levels!B:B,A1402,Levels!E:E),0) -> 10.035 | D1402: =IFERROR(AVERAGEIF(Levels!B:B,A1402,Levels!F:F),0) -> 6.725 | E1402: =_xlfn.MAXIFS(Levels!E:E,Levels!B:B,A1402) -> 18.89 | F1402: =_xlfn.MAXIFS(Levels!F:F,Levels!B:B,A1402) -> 6.78
A1403: notlsa | B1403: =COUNTIF(Levels!B:B,A1403) -> 3 | C1403: =IFERROR(AVERAGEIF(Levels!B:B,A1403,Levels!E:E),0) -> 24.043333 | D1403: =IFERROR(AVERAGEIF(Levels!B:B,A1403,Levels!F:F),0) -> 7.7433333 | E1403: =_xlfn.MAXIFS(Levels!E:E,Levels!B:B,A1403) -> 28 | F1403: =_xlfn.MAXIFS(Levels!F:F,Levels!B:B,A1403) -> 8
A1404: Komatic5 | B1404: =COUNTIF(Levels!B:B,A1404) -> 2 | C1404: =IFERROR(AVERAGEIF(Levels!B:B,A1404,Levels!E:E),0) -> 10.165 | D1404: =IFERROR(AVERAGEIF(Levels!B:B,A1404,Levels!F:F),0) -> 6.675 | E1404: =_xlfn.MAXIFS(Levels!E:E,Levels!B:B,A1404) -> 12.45 | F1404: =_xlfn.MAXIFS(Levels!F:F,Levels!B:B,A1404) -> 7.35
A1405: Selket | B1405: =COUNTIF(Levels!B:B,A1405) -> 1 | C1405: =IFERROR(AVERAGEIF(Levels!B:B,A1405,Levels!E:E),0) -> 7.25 | D1405: =IFERROR(AVERAGEIF(Levels!B:B,A1405,Levels!F:F),0) -> 4.67 | E1405: =_xlfn.MAXIFS(Levels!E:E,Levels!B:B,A1405) -> 7.25 | F1405: =_xlfn.MAXIFS(Levels!F:F,Levels!B:B,A1405) -> 4.67
A1406: Ajedaboss | B1406: =COUNTIF(Levels!B:B,A1406) -> 1 | C1406: =IFERROR(AVERAGEIF(Levels!B:B,A1406,Levels!E:E),0) -> 2.23 | D1406: =IFERROR(AVERAGEIF(Levels!B:B,A1406,Levels!F:F),0) -> 5.53 | E1406: =_xlfn.MAXIFS(Levels!E:E,Levels!B:B,A1406) -> 2.23 | F1406: =_xlfn.MAXIFS(Levels!F:F,Levels!B:B,A1406) -> 5.53
A1407: CHUZA | B1407: =COUNTIF(Levels!B:B,A1407) -> 3 | C1407: =IFERROR(AVERAGEIF(Levels!B:B,A1407,Levels!E:E),0) -> 16.493333 | D1407: =IFERROR(AVERAGEIF(Levels!B:B,A1407,Levels!F:F),0) -> 6.5033333 | E1407: =_xlfn.MAXIFS(Levels!E:E,Levels!B:B,A1407) -> 18.84 | F1407: =_xlfn.MAXIFS(Levels!F:F,Levels!B:B,A1407) -> 7.07
A1408: Rekeyame | B1408: =COUNTIF(Levels!B:B,A1408) -> 1 | C1408: =IFERROR(AVERAGEIF(Levels!B:B,A1408,Levels!E:E),0) -> 11 | D1408: =IFERROR(AVERAGEIF(Levels!B:B,A1408,Levels!F:F),0) -> 4 | E1408: =_xlfn.MAXIFS(Levels!E:E,Levels!B:B,A1408) -> 11 | F1408: =_xlfn.MAXIFS(Levels!F:F,Levels!B:B,A1408) -> 4
A1409: Maxos9Gang | B1409: =COUNTIF(Levels!B:B,A1409) -> 1 | C1409: =IFERROR(AVERAGEIF(Levels!B:B,A1409,Levels!E:E),0) -> 17 | D1409: =IFERROR(AVERAGEIF(Levels!B:B,A1409,Levels!F:F),0) -> 7 | E1409: =_xlfn.MAXIFS(Levels!E:E,Levels!B:B,A1409) -> 17 | F1409: =_xlfn.MAXIFS(Levels!F:F,Levels!B:B,A1409) -> 7
A1410: 1u49 | B1410: =COUNTIF(Levels!B:B,A1410) -> 3 | C1410: =IFERROR(AVERAGEIF(Levels!B:B,A1410,Levels!E:E),0) -> 1.67 | D1410: =IFERROR(AVERAGEIF(Levels!B:B,A1410,Levels!F:F),0) -> 6.6933333 | E1410: =_xlfn.MAXIFS(Levels!E:E,Levels!B:B,A1410) -> 2.5 | F1410: =_xlfn.MAXIFS(Levels!F:F,Levels!B:B,A1410) -> 7.22
A1411: ElectroBoy2217 | B1411: =COUNTIF(Levels!B:B,A1411) -> 1 | C1411: =IFERROR(AVERAGEIF(Levels!B:B,A1411,Levels!E:E),0) -> 6.24 | D1411: =IFERROR(AVERAGEIF(Levels!B:B,A1411,Levels!F:F),0) -> 7.16 | E1411: =_xlfn.MAXIFS(Levels!E:E,Levels!B:B,A1411) -> 6.24 | F1411: =_xlfn.MAXIFS(Levels!F:F,Levels!B:B,A1411) -> 7.16
... A3322: Uz3rr | B3322: =COUNTIF(Levels!B:B,A3322) -> 1 | C3322: =IFERROR(AVERAGEIF(Levels!B:B,A3322,Levels!E:E),0) -> 0 | D3322: =IFERROR(AVERAGEIF(Levels!B:B,A3322,Levels!F:F),0) -> 7.5 | E3322: =_xlfn.MAXIFS(Levels!E:E,Levels!B:B,A3322) -> 0 | F3322: =_xlfn.MAXIFS(Levels!F:F,Levels!B:B,A3322) -> 7.5

Sheet Dashboard

Sheet Featured

Sheet About
